articat/__init__.py
articat/artifact.py
articat/bq_artifact.py
articat/catalog.py
articat/catalog_datastore.py
articat/catalog_local.py
articat/cli.py
articat/config.py
articat/exceptions.py
articat/fs_artifact.py
articat/meta_artifact.py
articat/notebook_artifact.py
articat/py.typed
articat/tests/__init__.py
articat/tests/artifact_test.py
articat/tests/bq_artifact_test.py
articat/tests/catalog_datastore_test.py
articat/tests/catalog_local_test.py
articat/tests/cli_test.py
articat/tests/config_test.py
articat/tests/fs_artifact_test.py
articat/tests/meta_artifact_test.py
articat/tests/notebook_artifact_test.py
articat/tests/notebook_utils_test.py
articat/tests/utils.py
articat/tests/utils_test.py
articat/tests/test_files/dummy_notebook.ipynb
articat/utils/__init__.py
articat/utils/class_or_instance_method.py
articat/utils/datetime_utils.py
articat/utils/notebook_utils.py
articat/utils/path_utils.py
articat/utils/typing.py
articat/utils/utils.py
articat-0.2.0.data/scripts/articat
articat-0.2.0.dist-info/LICENSE
articat-0.2.0.dist-info/METADATA
articat-0.2.0.dist-info/WHEEL
articat-0.2.0.dist-info/top_level.txt
articat-0.2.0.dist-info/RECORD
