Metadata-Version: 2.2
Name: articat
Version: 0.2.0
Summary: articat: data artifact catalog
Home-page: https://github.com/related-sciences/articat
Author: Related Sciences LLC
Author-email: rav@related.vc
License: Apache
Keywords: data,catalog,metadata,data-discovery,data-catalog
Classifier: Development Status :: 3 - Alpha
Classifier: Intended Audience :: Developers
Classifier: License :: OSI Approved :: Apache Software License
Classifier: Operating System :: OS Independent
Classifier: Programming Language :: Python
Classifier: Programming Language :: Python :: 3
Requires-Python: >=3.11
License-File: LICENSE
Requires-Dist: fire>=0.4.0
Requires-Dist: fsspec>=2021.7.0
Requires-Dist: gcsfs>=2021.7.0
Requires-Dist: google-cloud-bigquery>=1.11
Requires-Dist: google-cloud-datastore>=2.1
Requires-Dist: papermill>=2.3
Requires-Dist: pydantic~=2.0
